{
  "title": "Twinkle Twinkle Little Star",
  "key": "twinkle twinkle little star",
  "time": "4/4",
  "isChristmas": false,
  "published": true,
  "bpm": 100,
  "tags": [
    "Easy"
  ],
  "origin": "French",
  "phrases": [
    6,
    13,
    20,
    27,
    34,
    41
  ],
  "entries": [
    {
      "notes": [
        {
          "note": "c",
          "time": "fourth",
          "lyrics": "Twin -"
        }
      ]
    },
    {
      "notes": [
        {
          "note": "c",
          "time": "fourth",
          "lyrics": "kle,"
        }
      ]
    },
    {
      "notes": [
        {
          "note": "g",
          "time": "fourth",
          "lyrics": "twin -"
        }
      ]
    },
    {
      "notes": [
        {
          "note": "g",
          "time": "fourth",
          "lyrics": "kle"
        }
      ]
    },
    {
      "notes": [
        {
          "note": "a",
          "time": "fourth",
          "lyrics": "lit -"
        }
      ]
    },
    {
      "notes": [
        {
          "note": "a",
          "time": "fourth",
          "lyrics": "tle"
        }
      ]
    },
    {
      "notes": [
        {
          "note": "g",
          "time": "half",
          "lyrics": "star,"
        }
      ]
    },
    {
      "notes": [
        {
          "note": "f",
          "time": "fourth",
          "lyrics": "How"
        }
      ]
    },
    {
      "notes": [
        {
          "note": "f",
          "time": "fourth",
          "lyrics": "I"
        }
      ]
    },
    {
      "notes": [
        {
          "note": "e",
          "time": "fourth",
          "lyrics": "won -"
        }
      ]
    },
    {
      "notes": [
        {
          "note": "e",
          "time": "fourth",
          "lyrics": "der"
        }
      ]
    },
    {
      "notes": [
        {
          "note": "d",
          "time": "fourth",
          "lyrics": "what"
        }
      ]
    },
    {
      "notes": [
        {
          "note": "d",
          "time": "fourth",
          "lyrics": "you"
        }
      ]
    },
    {
      "notes": [
        {
          "note": "c",
          "time": "half",
          "lyrics": "are."
        }
      ]
    },
    {
      "notes": [
        {
          "note": "g",
          "time": "fourth",
          "lyrics": "Up"
        }
      ]
    },
    {
      "notes": [
        {
          "note": "g",
          "time": "fourth",
          "lyrics": "a -"
        }
      ]
    },
    {
      "notes": [
        {
          "note": "f",
          "time": "fourth",
          "lyrics": "bove"
        }
      ]
    },
    {
      "notes": [
        {
          "note": "f",
          "time": "fourth",
          "lyrics": "the"
        }
      ]
    },
    {
      "notes": [
        {
          "note": "e",
          "time": "fourth",
          "lyrics": "world"
        }
      ]
    },
    {
      "notes": [
        {
          "note": "e",
          "time": "fourth",
          "lyrics": "so"
        }
      ]
    },
    {
      "notes": [
        {
          "note": "d",
          "time": "half",
          "lyrics": "high,"
        }
      ]
    },
    {
      "notes": [
        {
          "note": "g",
          "time": "fourth",
          "lyrics": "Like"
        }
      ]
    },
    {
      "notes": [
        {
          "note": "g",
          "time": "fourth",
          "lyrics": "a"
        }
      ]
    },
    {
      "notes": [
        {
          "note": "f",
          "time": "fourth",
          "lyrics": "dia -"
        }
      ]
    },
    {
      "notes": [
        {
          "note": "f",
          "time": "fourth",
          "lyrics": "mond"
        }
      ]
    },
    {
      "notes": [
        {
          "note": "e",
          "time": "fourth",
          "lyrics": "in"
        }
      ]
    },
    {
      "notes": [
        {
          "note": "e",
          "time": "fourth",
          "lyrics": "the"
        }
      ]
    },
    {
      "notes": [
        {
          "note": "d",
          "time": "half",
          "lyrics": "sky."
        }
      ]
    },
    {
      "notes": [
        {
          "note": "c",
          "time": "fourth",
          "lyrics": "Twin -"
        }
      ]
    },
    {
      "notes": [
        {
          "note": "c",
          "time": "fourth",
          "lyrics": "kle,"
        }
      ]
    },
    {
      "notes": [
        {
          "note": "g",
          "time": "fourth",
          "lyrics": "twin -"
        }
      ]
    },
    {
      "notes": [
        {
          "note": "g",
          "time": "fourth",
          "lyrics": "kle"
        }
      ]
    },
    {
      "notes": [
        {
          "note": "a",
          "time": "fourth",
          "lyrics": "lit -"
        }
      ]
    },
    {
      "notes": [
        {
          "note": "a",
          "time": "fourth",
          "lyrics": "tle"
        }
      ]
    },
    {
      "notes": [
        {
          "note": "g",
          "time": "half",
          "lyrics": "star,"
        }
      ]
    },
    {
      "notes": [
        {
          "note": "f",
          "time": "fourth",
          "lyrics": "How"
        }
      ]
    },
    {
      "notes": [
        {
          "note": "f",
          "time": "fourth",
          "lyrics": "I"
        }
      ]
    },
    {
      "notes": [
        {
          "note": "e",
          "time": "fourth",
          "lyrics": "won -"
        }
      ]
    },
    {
      "notes": [
        {
          "note": "e",
          "time": "fourth",
          "lyrics": "der"
        }
      ]
    },
    {
      "notes": [
        {
          "note": "d",
          "time": "fourth",
          "lyrics": "what"
        }
      ]
    },
    {
      "notes": [
        {
          "note": "d",
          "time": "fourth",
          "lyrics": "you"
        }
      ]
    },
    {
      "notes": [
        {
          "note": "c",
          "time": "half",
          "lyrics": "are."
        }
      ]
    }
  ]
}